zyt/__init__.py
zyt/__main__.py
zyt/auth.py
zyt/cli.py
zyt/config.py
zyt/gitops.py
zyt/registry.py
zyt/version.py
zyt_si-2.0.2.dist-info/licenses/LICENSE
zyt_si-2.0.2.dist-info/METADATA
zyt_si-2.0.2.dist-info/WHEEL
zyt_si-2.0.2.dist-info/entry_points.txt
zyt_si-2.0.2.dist-info/top_level.txt
zyt_si-2.0.2.dist-info/RECORD
