Metadata-Version: 2.4
Name: zyt-si
Version: 2.0.2
Summary: Git-based package manager CLI
Author: Samail Islam
License: GNU General Public License v3
Requires-Python: >=3.8
License-File: LICENSE
Dynamic: license-file
